[
            {
                  "img2": "https://saksham-guptaa.github.io/hackbpitAPI/farm1.jpg",
                  "title": "Best Location"
            },
            {
                  "img2": "https://saksham-guptaa.github.io/hackbpitAPI/farm2.jpg",
                  "title": "Best Location"
            },
            {
                  "img2": "https://saksham-guptaa.github.io/hackbpitAPI/farm3.jpg",
                  "title": "On HighWay"
            },
            {
                  "img2": "https://saksham-guptaa.github.io/hackbpitAPI/farm5.jpg",
                  "title": "Full Access"
            }
]
